LICENSE
MANIFEST.in
README.rst
pyproject.toml
setup.cfg
setup.py
src/ua_parser/__init__.py
src/ua_parser/user_agent_parser.py
src/ua_parser_up2date.egg-info/PKG-INFO
src/ua_parser_up2date.egg-info/SOURCES.txt
src/ua_parser_up2date.egg-info/dependency_links.txt
src/ua_parser_up2date.egg-info/requires.txt
src/ua_parser_up2date.egg-info/top_level.txt
tests/test_legacy.py
uap-core/CONTRIBUTING.md
uap-core/LICENSE
uap-core/README.md
uap-core/package.json
uap-core/regexes.yaml
uap-core/.github/workflows/ci.yml
uap-core/docs/specification.md
uap-core/test_resources/additional_os_tests.yaml
uap-core/test_resources/firefox_user_agent_strings.txt
uap-core/test_resources/firefox_user_agent_strings.yaml
uap-core/test_resources/opera_mini_user_agent_strings.yaml
uap-core/test_resources/pgts_browser_list-orig.yaml
uap-core/test_resources/pgts_browser_list.txt
uap-core/test_resources/pgts_browser_list.yaml
uap-core/test_resources/podcasting_user_agent_strings.yaml
uap-core/test_resources/transform-pgts_browser_list.pl
uap-core/tests/test_device.yaml
uap-core/tests/test_os.yaml
uap-core/tests/test_ua.yaml