Metadata-Version: 2.1
Name: ua-parser-up2date
Version: 0.18.1
Summary: Python port of Browserscope's user agent parser
Author-email: Stephen Lamm <slamm@google.com>, PBS <no-reply@pbs.org>, Selwin Ong <selwin.ong@gmail.com>, Matt Robenolt <matt@ydekproductions.com>, Lindsey Simon <lsimon@commoner.com>
Maintainer-email: masklinn <uap@masklinn.net>
License: Apache 2.0
Project-URL: repository, https://github.com/robd003/uap-python-up2date
Classifier: Development Status :: 4 - Beta
Classifier: Environment :: Web Environment
Classifier: Intended Audience :: Developers
Classifier: Operating System :: OS Independent
Classifier: License :: OSI Approved :: Apache Software License
Classifier: Programming Language :: Python
Classifier: Topic :: Internet :: WWW/HTTP
Classifier: Topic :: Software Development :: Libraries :: Python Modules
Classifier: Programming Language :: Python
Classifier: Programming Language :: Python :: 3.9
Classifier: Programming Language :: Python :: 3.10
Classifier: Programming Language :: Python :: 3.11
Classifier: Programming Language :: Python :: Implementation :: CPython
Classifier: Programming Language :: Python :: Implementation :: PyPy
Requires-Python: >=3.9
Provides-Extra: yaml
License-File: LICENSE
